{
  "users": [
    {
      "email": "first1@mail.com",
      "password": "$2a$10$zLNJP8OEGbUqfbFG9Uzg1uYoXn4WxAd1EhWO4xw51ifDINpGaV8YS",
      "username": "First1",
      "id": 1,
      "firstName": "fulano",
      "lastName": "de tal"
    },
    {
      "email": "teste2@mail.com",
      "password": "$2a$10$W6J3XdalYXJtqI8mNaz5p.5YJg3Mk2H/6NFN4dkCbAaIt14vmJxTO",
      "username": "teste2",
      "todo": [],
      "id": 2
    },
    {
      "email": "first@mail.com",
      "password": "$2a$10$vniq0/SG4Dt4nF3jgp2joODRt9SqBt40pzd502NCpAAY/hg3KWQ8C",
      "id": 3
    },
    {
      "email": "first2@mail.com",
      "password": "$2a$10$rbVaC28sGVGGSD0WXkVKx.WXCczIcU4jI/KLb8iDYH/FzgCXFqhVa",
      "firstName": "sdf",
      "confirmPassword": "123456",
      "id": 4
    }
  ],
  "clients": [
    {
      "name": "dfgfdg",
      "cpf": "35345",
      "email": "kenzo@mail.com",
      "tel": "(23) 4234-2342",
      "cel": "(23) 4234-23423",
      "postalCode": "94820-170",
      "street": "Rua Itararé",
      "number": "4",
      "city": "Alvorada",
      "state": "RS",
      "district": "Sumaré",
      "profInfo": "sasf",
      "clientSince": "2021-09-13",
      "lastContact": "2021-09-13",
      "observations": "sfsdfsf",
      "userId": 1,
      "id": 2
    },
    {
      "name": "teste",
      "cpf": "234234",
      "email": "kenzo@email.com",
      "tel": "(32) 4234-2342",
      "cel": "(23) 4234-23423",
      "postalCode": "94820-170",
      "street": "Rua Itararé",
      "number": "3",
      "city": "Alvorada",
      "state": "RS",
      "district": "Sumaré",
      "profInfo": "dfsf",
      "clientSince": "2021-09-13",
      "lastContact": "2021-09-13",
      "observations": "sgdfgsdfg",
      "userId": 1,
      "id": 3
    },
    {
      "name": "dsfg",
      "cpf": "",
      "email": "",
      "tel": "(43) 5345-3453",
      "cel": "(34) 5345-34534",
      "postalCode": "94820-170",
      "street": "Rua Itararé",
      "number": "",
      "city": "Alvorada",
      "state": "RS",
      "district": "Sumaré",
      "profInfo": "",
      "clientSince": "",
      "lastContact": "",
      "observations": "",
      "contracts": [],
      "userId": 1,
      "id": 4
    },
    {
      "name": "fghfhg",
      "cpf": "",
      "email": "",
      "tel": "(24) 2342-4234",
      "cel": "(32) 4342-42432",
      "postalCode": "94820-170",
      "street": "Rua Itararé",
      "number": "",
      "city": "Alvorada",
      "state": "RS",
      "district": "Sumaré",
      "profInfo": "",
      "clientSince": "",
      "lastContact": "",
      "observations": "",
      "contracts": [],
      "userId": 1,
      "id": 7
    },
    {
      "name": "fgh",
      "cpf": "",
      "email": "",
      "tel": "(35) 3453-4534",
      "cel": "(34) 5345-35353",
      "postalCode": "94820-170",
      "street": "Rua Itararé",
      "number": "",
      "city": "Alvorada",
      "state": "RS",
      "district": "Sumaré",
      "profInfo": "",
      "clientSince": "",
      "lastContact": "",
      "observations": "",
      "contracts": [],
      "userId": 1,
      "id": 8
    },
    {
      "name": "testereset",
      "cpf": "",
      "email": "",
      "tel": "",
      "cel": "",
      "postalCode": "",
      "street": "",
      "number": "",
      "city": "",
      "state": "",
      "district": "",
      "profInfo": "",
      "clientSince": "",
      "lastContact": "",
      "observations": "",
      "contracts": [],
      "userId": 1,
      "id": 9
    },
    {
      "name": "dfgdfg",
      "cpf": "",
      "email": "",
      "tel": "",
      "cel": "",
      "postalCode": "",
      "street": "",
      "number": "",
      "city": "",
      "state": "",
      "district": "",
      "profInfo": "",
      "clientSince": "",
      "lastContact": "",
      "observations": "",
      "contracts": [],
      "userId": 1,
      "id": 10
    },
    {
      "name": "fhfgh",
      "cpf": "",
      "email": "",
      "tel": "",
      "cel": "",
      "postalCode": "",
      "street": "",
      "number": "",
      "city": "",
      "state": "",
      "district": "",
      "profInfo": "",
      "observations": "",
      "contracts": [],
      "userId": 1,
      "id": 11
    },
    {
      "name": "fgh",
      "cpf": "",
      "email": "",
      "tel": "",
      "cel": "",
      "postalCode": "",
      "street": "f",
      "number": "",
      "city": "",
      "state": "",
      "district": "",
      "profInfo": "",
      "observations": "",
      "contracts": [],
      "userId": 1,
      "id": 12
    },
    {
      "name": "dfgdfg",
      "cpf": "",
      "email": "",
      "tel": "",
      "cel": "",
      "postalCode": "",
      "street": "",
      "number": "",
      "city": "",
      "state": "",
      "district": "",
      "profInfo": "",
      "observations": "",
      "contracts": [],
      "userId": 1,
      "id": 13
    },
    {
      "name": "dfg",
      "cpf": "",
      "email": "",
      "tel": "",
      "cel": "",
      "postalCode": "",
      "street": "dfg",
      "number": "",
      "city": "",
      "state": "",
      "district": "",
      "profInfo": "",
      "observations": "",
      "contracts": [],
      "userId": 1,
      "id": 14
    },
    {
      "name": "dfg",
      "cpf": "",
      "email": "",
      "tel": "",
      "cel": "",
      "postalCode": "",
      "street": "",
      "number": "",
      "city": "",
      "state": "",
      "district": "",
      "profInfo": "",
      "observations": "",
      "contracts": [],
      "userId": 1,
      "id": 15
    },
    {
      "name": "dfg",
      "cpf": "",
      "email": "",
      "tel": "",
      "cel": "",
      "postalCode": "",
      "street": "",
      "number": "",
      "city": "",
      "state": "",
      "district": "",
      "profInfo": "",
      "observations": "",
      "contracts": [],
      "userId": 1,
      "id": 16
    },
    {
      "name": "lll",
      "cpf": "",
      "email": "",
      "tel": "",
      "cel": "",
      "postalCode": "",
      "street": "",
      "number": "",
      "city": "",
      "state": "",
      "district": "",
      "profInfo": "",
      "observations": "",
      "contracts": [],
      "userId": 1,
      "id": 17
    },
    {
      "name": "sfdsf",
      "cpf": "34534",
      "email": "",
      "tel": "(45) 3453-5345",
      "cel": "",
      "postalCode": "",
      "number": "",
      "profInfo": "",
      "clientSince": "2021-09-13T14:27:15.722Z",
      "lastContact": "2021-09-13T14:27:15.722Z",
      "observations": "",
      "street": "",
      "city": "",
      "district": "",
      "state": "",
      "contracts": [],
      "userId": 1,
      "id": 18
    },
    {
      "name": "teste numeros",
      "cpf": "3253",
      "email": "",
      "tel": "",
      "cel": "",
      "postalCode": "",
      "number": "",
      "profInfo": "",
      "clientSince": "2021-09-13T14:42:18.163Z",
      "lastContact": "2021-09-13T14:42:18.163Z",
      "observations": "",
      "street": "",
      "city": "",
      "district": "",
      "state": "",
      "contracts": [],
      "userId": 1,
      "id": 19
    },
    {
      "name": "sfdgdsfgdfsgsdfg",
      "cpf": "",
      "email": "",
      "tel": "",
      "cel": "",
      "postalCode": "",
      "number": "",
      "profInfo": "",
      "clientSince": "2021-09-14T12:30:20.962Z",
      "lastContact": "2021-09-14T12:30:20.962Z",
      "observations": "",
      "street": "",
      "city": "",
      "district": "",
      "state": "",
      "contracts": [],
      "userId": 1,
      "id": 20
    }
  ],
  "services": [
    {
      "title": "Primeiro",
      "description": "The first service",
      "language": "Plankalkül",
      "budget": "100000.01",
      "finalValue": "",
      "userId": 1,
      "id": 1
    },
    {
      "name": "joazinho2",
      "userId": 1,
      "id": 3
    }
  ],
  "contracts": [
    {
      "service": "id do serviço",
      "status": "Concluído",
      "userId": 1,
      "clientId": 2,
      "id": 2
    }
  ]
}